pomcli/__about__.py
pomcli/__init__.py
pomcli/pomodoro.py
pomcli-0.2.0.dist-info/METADATA
pomcli-0.2.0.dist-info/WHEEL
pomcli-0.2.0.dist-info/entry_points.txt
pomcli-0.2.0.dist-info/licenses/LICENSE.txt
pomcli-0.2.0.dist-info/RECORD
