Metadata-Version: 2.4
Name: PomCli
Version: 0.2.0
Summary: A simple Pomodoro timer CLI tool.
Project-URL: Documentation, https://github.com/YanivGrosskopf/PomCli#readme
Project-URL: Issues, https://github.com/YanivGrosskopf/PomCli/issues
Project-URL: Source, https://github.com/YanivGrosskopf/PomCli
Author-email: Yaniv Grosskopf <qywoec@gmail.com>
License-Expression: MIT
License-File: LICENSE.txt
Classifier: Development Status :: 4 - Beta
Classifier: Programming Language :: Python
Classifier: Programming Language :: Python :: 3.8
Classifier: Programming Language :: Python :: 3.9
Classifier: Programming Language :: Python :: 3.10
Classifier: Programming Language :: Python :: 3.11
Classifier: Programming Language :: Python :: 3.12
Classifier: Programming Language :: Python :: Implementation :: CPython
Classifier: Programming Language :: Python :: Implementation :: PyPy
Requires-Python: >=3.8
Requires-Dist: tqdm>=4.0.0
